{
    "parent": "minecraft:item/handheld",
    "loader": "forge:separate_transforms",
      "textures": {
		"particle": "tfc:item/food/cooked_chicken"
	},
    "base": {
        "parent": "brewinandchewin:block/coaster_cooked_chicken"
    },
    "perspectives": {
        "gui": {
            "parent": "tfc:item/food/cooked_chicken_item"
        },
        "ground": {
            "parent": "brewinandchewin:block/coaster_cooked_chicken"
        },
        "fixed": {
            "parent": "brewinandchewin:block/coaster_cooked_chicken"
        }
    }
}