{
  "itemSpecific": {
    "minecraft:lantern": {
      "kind": "LANTERN",
      "armKind": "LANTERN",
      "physics": [
        {
          "name": "FULL_PENDULUM",
          "limitDeg": 40.0,
          "force": 0.03,
          "speed": 1.0,
          "cameraSens": 0.75,
          "gravity": 25.0,
          "handSpace": true
        }
      ],
      "disable_sprint_lateral_tilt": true,
      "keep_arm_tuning": true,
      "transforms": {
        "right": {
          "scale": 1.01,
          "offX": 0.15625,
          "offY": -0.5568181,
          "offZ": 0.1392045,
          "rotX": -37.84091,
          "rotY": 35.0,
          "rotZ": 8.181808,
          "pivotX": -0.109999955,
          "pivotY": -0.00999999,
          "pivotZ": -0.01999998,
          "physics": "FULL_PENDULUM"
        },
        "left": {
          "scale": 1.01,
          "offX": -0.15625,
          "offY": -0.5568181,
          "offZ": 0.1392045,
          "rotX": -37.84091,
          "rotY": -35.0,
          "rotZ": -8.181808,
          "pivotX": 0.109999955,
          "pivotY": -0.00999999,
          "pivotZ": -0.01999998,
          "physics": "FULL_PENDULUM"
        }
      },
      "armTransforms": {
        "right": {
          "scale": 1.0,
          "offX": 0.0,
          "offY": -0.4,
          "offZ": 0.0,
          "rotX": -17.0,
          "rotY": 0.0,
          "rotZ": 0.0,
          "pivotX": 0.0,
          "pivotY": 0.0,
          "pivotZ": 0.0
        }
      }
    }
  },
  "customGroups": [
    {
      "name": "tfc_lamp",
      "items": [
        "tfc:metal/lamp/bismuth_bronze",
        "tfc:metal/unfinished_lamp/bismuth_bronze",
        "tfc:metal/lamp/black_bronze",
        "tfc:metal/unfinished_lamp/black_bronze",
        "tfc:metal/lamp/bronze",
        "tfc:metal/unfinished_lamp/bronze",
        "tfc:metal/lamp/copper",
        "tfc:metal/unfinished_lamp/copper",
        "tfc:metal/lamp/wrought_iron",
        "tfc:metal/unfinished_lamp/wrought_iron",
        "tfc:metal/lamp/steel",
        "tfc:metal/unfinished_lamp/steel",
        "tfc:metal/lamp/black_steel",
        "tfc:metal/unfinished_lamp/black_steel",
        "tfc:metal/lamp/blue_steel",
        "tfc:metal/unfinished_lamp/blue_steel",
        "tfc:metal/lamp/red_steel",
        "tfc:metal/unfinished_lamp/red_steel"
      ]
    }
  ],
  "item": {
    "tfc_lamp": {
      "kind": "LANTERN",
      "armKind": "LANTERN",
      "physics": [
        {
          "name": "FULL_PENDULUM",
          "limitDeg": 40.0,
          "force": 0.03,
          "speed": 1.0,
          "cameraSens": 0.75,
          "gravity": 25.0,
          "handSpace": true
        }
      ],
      "disable_sprint_lateral_tilt": true,
      "keep_arm_tuning": true,
      "transforms": {
        "right": {
          "scale": 1.01,
          "offX": 0.15625,
          "offY": -0.5568181,
          "offZ": 0.1392045,
          "rotX": -37.84091,
          "rotY": 35.0,
          "rotZ": 8.181808,
          "pivotX": -0.109999955,
          "pivotY": -0.00999999,
          "pivotZ": -0.01999998,
          "physics": "FULL_PENDULUM"
        },
        "left": {
          "scale": 1.01,
          "offX": -0.15625,
          "offY": -0.5568181,
          "offZ": 0.1392045,
          "rotX": -37.84091,
          "rotY": -35.0,
          "rotZ": -8.181808,
          "pivotX": 0.109999955,
          "pivotY": -0.00999999,
          "pivotZ": -0.01999998,
          "physics": "FULL_PENDULUM"
        }
      },
      "armTransforms": {
        "right": {
          "scale": 1.0,
          "offX": 0.0,
          "offY": -0.4,
          "offZ": 0.0,
          "rotX": -17.0,
          "rotY": 0.0,
          "rotZ": 0.0,
          "pivotX": 0.0,
          "pivotY": 0.0,
          "pivotZ": 0.0
        }
      }
    }
  }
}