{
    "name": "crash_landed_refugees_crew_members",
    "attributes": {
        "strength": 8,
        "health": 13,
        "focus": 11,
        "stamina": 11,
        "endurance": 8,
        "intelligence": 12,
        "agility": 10,
        "skill": 10,
        "luck": 7
    },
    "startItems": [
        {
            "item": "ad_astra:ti_69",
            "count": 1
        },
        {
            "item": "legendarysurvivaloverhaul:morphine",
            "count": 1
        },
        {
            "item": "minecraft:spyglass",
            "count": 1
        },
        {
            "item": "textile:cotton_shirt",
            "count": 1
        },
        {
            "item": "firmalife:food/hardtack",
            "count": 5
        },
        {
            "item": "wildfire:instant_gel_classic",
            "count": 5
        }
    ],
    "displayCondition": []
}